src/easy_tui/__init__.py
src/easy_tui/examples.py
src/easy_tui/menu.py
src/easy_tui/window.py
easy_x_tui-0.0.1.dist-info/METADATA
easy_x_tui-0.0.1.dist-info/WHEEL
easy_x_tui-0.0.1.dist-info/licenses/LICENSE.md
easy_x_tui-0.0.1.dist-info/RECORD
