Metadata-Version: 2.1
Name: easy-x-tui
Version: 0.0.1
Summary: A lightweight, cross-platform utility for creating TUIs
Project-URL: Source Code, https://github.com/stephenlf/easy-tui
Project-URL: Homepage, https://stephenlf.github.io/easy-tui
Author-email: Stephen Funk <stephenlfunk@gmail.com>
License-File: LICENSE.md
Classifier: License :: OSI Approved :: MIT License
Classifier: Operating System :: OS Independent
Classifier: Programming Language :: Python :: 3
Requires-Python: >=3.7
